{
  "CF100399781": {
    "contest_id": 844,
    "language": "GNU C++17 (64)",
    "path": "codeforces/844/B.cpp",
    "problem_index": "B",
    "problem_name": "Rectangles",
    "problem_url": "https://codeforces.com/contest/844/problem/B",
    "submission_id": "CF100399781",
    "submission_url": "https://codeforces.com/contest/844/submission/100399781",
    "tags": [
      "combinatorics",
      "math",
      "*1300"
    ],
    "timestamp": "Dec/05/2020 00:28"
  },
  "CF100424875": {
    "contest_id": 312,
    "language": "GNU C++17 (64)",
    "path": "codeforces/312/B.cpp",
    "problem_index": "B",
    "problem_name": "Archer",
    "problem_url": "https://codeforces.com/contest/312/problem/B",
    "submission_id": "CF100424875",
    "submission_url": "https://codeforces.com/contest/312/submission/100424875",
    "tags": [
      "math",
      "probabilities",
      "*1300"
    ],
    "timestamp": "Dec/05/2020 12:31"
  },
  "CF100437200": {
    "contest_id": 1102,
    "language": "GNU C++17 (64)",
    "path": "codeforces/1102/E.cpp",
    "problem_index": "E",
    "problem_name": "Monotonic Renumeration",
    "problem_url": "https://codeforces.com/contest/1102/problem/E",
    "submission_id": "CF100437200",
    "submission_url": "https://codeforces.com/contest/1102/submission/100437200",
    "tags": [
      "combinatorics",
      "sortings",
      "*1700"
    ],
    "timestamp": "Dec/05/2020 14:28"
  },
  "CF100536131": {
    "contest_id": 1450,
    "language": "GNU C++17 (64)",
    "path": "codeforces/1450/A.cpp",
    "problem_index": "A",
    "problem_name": "Avoid Trygub",
    "problem_url": "https://codeforces.com/contest/1450/problem/A",
    "submission_id": "CF100536131",
    "submission_url": "https://codeforces.com/contest/1450/submission/100536131",
    "tags": [
      "constructive algorithms",
      "sortings",
      "*800"
    ],
    "timestamp": "Dec/06/2020 20:18"
  },
  "CF100540986": {
    "contest_id": 1450,
    "language": "GNU C++17 (64)",
    "path": "codeforces/1450/B.cpp",
    "problem_index": "B",
    "problem_name": "Balls of Steel",
    "problem_url": "https://codeforces.com/contest/1450/problem/B",
    "submission_id": "CF100540986",
    "submission_url": "https://codeforces.com/contest/1450/submission/100540986",
    "tags": [
      "brute force",
      "geometry",
      "greedy",
      "*1000"
    ],
    "timestamp": "Dec/06/2020 20:27"
  },
  "CF100618554": {
    "contest_id": 621,
    "language": "GNU C++17 (64)",
    "path": "codeforces/621/C.cpp",
    "problem_index": "C",
    "problem_name": "Wet Shark and Flowers",
    "problem_url": "https://codeforces.com/contest/621/problem/C",
    "submission_id": "CF100618554",
    "submission_url": "https://codeforces.com/contest/621/submission/100618554",
    "tags": [
      "combinatorics",
      "math",
      "number theory",
      "probabilities",
      "*1700"
    ],
    "timestamp": "Dec/07/2020 15:51"
  },
  "CF100638784": {
    "contest_id": 518,
    "language": "GNU C++17 (64)",
    "path": "codeforces/518/D.cpp",
    "problem_index": "D",
    "problem_name": "Ilya and Escalator",
    "problem_url": "https://codeforces.com/contest/518/problem/D",
    "submission_id": "CF100638784",
    "submission_url": "https://codeforces.com/contest/518/submission/100638784",
    "tags": [
      "combinatorics",
      "dp",
      "math",
      "probabilities",
      "*1700"
    ],
    "timestamp": "Dec/07/2020 20:43"
  },
  "CF100912327": {
    "contest_id": 1461,
    "language": "GNU C++17 (64)",
    "path": "codeforces/1461/A.cpp",
    "problem_index": "A",
    "problem_name": "String Generation",
    "problem_url": "https://codeforces.com/contest/1461/problem/A",
    "submission_id": "CF100912327",
    "submission_url": "https://codeforces.com/contest/1461/submission/100912327",
    "tags": [
      "constructive algorithms",
      "greedy",
      "*800"
    ],
    "timestamp": "Dec/11/2020 20:08"
  },
  "CF100966180": {
    "contest_id": 1461,
    "language": "GNU C++17 (64)",
    "path": "codeforces/1461/C.cpp",
    "problem_index": "C",
    "problem_name": "Random Events",
    "problem_url": "https://codeforces.com/contest/1461/problem/C",
    "submission_id": "CF100966180",
    "submission_url": "https://codeforces.com/contest/1461/submission/100966180",
    "tags": [
      "dp",
      "math",
      "probabilities",
      "*1500"
    ],
    "timestamp": "Dec/11/2020 23:44"
  },
  "CF101251396": {
    "contest_id": 1144,
    "language": "GNU C++17 (64)",
    "path": "codeforces/1144/F.cpp",
    "problem_index": "F",
    "problem_name": "Graph Without Long Directed Paths",
    "problem_url": "https://codeforces.com/contest/1144/problem/F",
    "submission_id": "CF101251396",
    "submission_url": "https://codeforces.com/contest/1144/submission/101251396",
    "tags": [
      "dfs and similar",
      "graphs",
      "*1700"
    ],
    "timestamp": "Dec/15/2020 18:36"
  },
  "CF101260489": {
    "contest_id": 1462,
    "language": "GNU C++17 (64)",
    "path": "codeforces/1462/A.cpp",
    "problem_index": "A",
    "problem_name": "Favorite Sequence",
    "problem_url": "https://codeforces.com/contest/1462/problem/A",
    "submission_id": "CF101260489",
    "submission_url": "https://codeforces.com/contest/1462/submission/101260489",
    "tags": [
      "implementation",
      "two pointers",
      "*800"
    ],
    "timestamp": "Dec/15/2020 20:08"
  },
  "CF101268243": {
    "contest_id": 1462,
    "language": "GNU C++17 (64)",
    "path": "codeforces/1462/B.cpp",
    "problem_index": "B",
    "problem_name": "Last Year's Substring",
    "problem_url": "https://codeforces.com/contest/1462/problem/B",
    "submission_id": "CF101268243",
    "submission_url": "https://codeforces.com/contest/1462/submission/101268243",
    "tags": [
      "dp",
      "implementation",
      "strings",
      "*800"
    ],
    "timestamp": "Dec/15/2020 20:15"
  },
  "CF101291172": {
    "contest_id": 1462,
    "language": "GNU C++14",
    "path": "codeforces/1462/C.cpp",
    "problem_index": "C",
    "problem_name": "Unique Number",
    "problem_url": "https://codeforces.com/contest/1462/problem/C",
    "submission_id": "CF101291172",
    "submission_url": "https://codeforces.com/contest/1462/submission/101291172",
    "tags": [
      "brute force",
      "greedy",
      "math",
      "*900"
    ],
    "timestamp": "Dec/15/2020 20:39"
  },
  "CF101397820": {
    "contest_id": 1461,
    "language": "GNU C++14",
    "path": "codeforces/1461/D.cpp",
    "problem_index": "D",
    "problem_name": "Divide and Summarize",
    "problem_url": "https://codeforces.com/contest/1461/problem/D",
    "submission_id": "CF101397820",
    "submission_url": "https://codeforces.com/contest/1461/submission/101397820",
    "tags": [
      "binary search",
      "brute force",
      "data structures",
      "divide and conquer",
      "implementation",
      "sortings",
      "*1600"
    ],
    "timestamp": "Dec/16/2020 13:43"
  },
  "CF101416503": {
    "contest_id": 1461,
    "language": "GNU C++14",
    "path": "codeforces/1461/E.cpp",
    "problem_index": "E",
    "problem_name": "Water Level",
    "problem_url": "https://codeforces.com/contest/1461/problem/E",
    "submission_id": "CF101416503",
    "submission_url": "https://codeforces.com/contest/1461/submission/101416503",
    "tags": [
      "brute force",
      "graphs",
      "greedy",
      "implementation",
      "math",
      "*2200"
    ],
    "timestamp": "Dec/16/2020 16:33"
  },
  "CF101423208": {
    "contest_id": 472,
    "language": "GNU C++14",
    "path": "codeforces/472/A.cpp",
    "problem_index": "A",
    "problem_name": "Design Tutorial: Learn from Math",
    "problem_url": "https://codeforces.com/contest/472/problem/A",
    "submission_id": "CF101423208",
    "submission_url": "https://codeforces.com/contest/472/submission/101423208",
    "tags": [
      "math",
      "number theory",
      "*800"
    ],
    "timestamp": "Dec/16/2020 17:59"
  },
  "CF101424357": {
    "contest_id": 876,
    "language": "GNU C++14",
    "path": "codeforces/876/B.cpp",
    "problem_index": "B",
    "problem_name": "Divisiblity of Differences",
    "problem_url": "https://codeforces.com/contest/876/problem/B",
    "submission_id": "CF101424357",
    "submission_url": "https://codeforces.com/contest/876/submission/101424357",
    "tags": [
      "implementation",
      "math",
      "number theory",
      "*1300"
    ],
    "timestamp": "Dec/16/2020 18:13"
  },
  "CF101456333": {
    "contest_id": 1266,
    "language": "GNU C++14",
    "path": "codeforces/1266/C.cpp",
    "problem_index": "C",
    "problem_name": "Diverse Matrix",
    "problem_url": "https://codeforces.com/contest/1266/problem/C",
    "submission_id": "CF101456333",
    "submission_url": "https://codeforces.com/contest/1266/submission/101456333",
    "tags": [
      "constructive algorithms",
      "greedy",
      "math",
      "number theory",
      "*1400"
    ],
    "timestamp": "Dec/17/2020 00:16"
  },
  "CF101480121": {
    "contest_id": 1242,
    "language": "GNU C++14",
    "path": "codeforces/1242/A.cpp",
    "problem_index": "A",
    "problem_name": "Tile Painting",
    "problem_url": "https://codeforces.com/contest/1242/problem/A",
    "submission_id": "CF101480121",
    "submission_url": "https://codeforces.com/contest/1242/submission/101480121",
    "tags": [
      "constructive algorithms",
      "math",
      "number theory",
      "*1500"
    ],
    "timestamp": "Dec/17/2020 12:48"
  },
  "CF101535266": {
    "contest_id": 1463,
    "language": "GNU C++14",
    "path": "codeforces/1463/B.cpp",
    "problem_index": "B",
    "problem_name": "Find The Array",
    "problem_url": "https://codeforces.com/contest/1463/problem/B",
    "submission_id": "CF101535266",
    "submission_url": "https://codeforces.com/contest/1463/submission/101535266",
    "tags": [
      "bitmasks",
      "constructive algorithms",
      "greedy",
      "*1400"
    ],
    "timestamp": "Dec/17/2020 20:34"
  },
  "CF101539764": {
    "contest_id": 1463,
    "language": "GNU C++14",
    "path": "codeforces/1463/A.cpp",
    "problem_index": "A",
    "problem_name": "Dungeon",
    "problem_url": "https://codeforces.com/contest/1463/problem/A",
    "submission_id": "CF101539764",
    "submission_url": "https://codeforces.com/contest/1463/submission/101539764",
    "tags": [
      "binary search",
      "math",
      "*1100"
    ],
    "timestamp": "Dec/17/2020 20:40"
  },
  "CF101633599": {
    "contest_id": 1462,
    "language": "GNU C++14",
    "path": "codeforces/1462/D.cpp",
    "problem_index": "D",
    "problem_name": "Add to Neighbour and Remove",
    "problem_url": "https://codeforces.com/contest/1462/problem/D",
    "submission_id": "CF101633599",
    "submission_url": "https://codeforces.com/contest/1462/submission/101633599",
    "tags": [
      "greedy",
      "math",
      "number theory",
      "*1400"
    ],
    "timestamp": "Dec/18/2020 17:07"
  },
  "CF101662938": {
    "contest_id": 1462,
    "language": "GNU C++14",
    "path": "codeforces/1462/F.cpp",
    "problem_index": "F",
    "problem_name": "The Treasure of The Segments",
    "problem_url": "https://codeforces.com/contest/1462/problem/F",
    "submission_id": "CF101662938",
    "submission_url": "https://codeforces.com/contest/1462/submission/101662938",
    "tags": [
      "binary search",
      "data structures",
      "greedy",
      "*1800"
    ],
    "timestamp": "Dec/18/2020 22:32"
  },
  "CF101758072": {
    "contest_id": 1459,
    "language": "GNU C++17 (64)",
    "path": "codeforces/1459/C.cpp",
    "problem_index": "C",
    "problem_name": "Row GCD",
    "problem_url": "https://codeforces.com/contest/1459/problem/C",
    "submission_id": "CF101758072",
    "submission_url": "https://codeforces.com/contest/1459/submission/101758072",
    "tags": [
      "math",
      "number theory",
      "*1600"
    ],
    "timestamp": "Dec/19/2020 16:42"
  },
  "CF101763008": {
    "contest_id": 1459,
    "language": "GNU C++17 (64)",
    "path": "codeforces/1459/B.cpp",
    "problem_index": "B",
    "problem_name": "Move and Turn",
    "problem_url": "https://codeforces.com/contest/1459/problem/B",
    "submission_id": "CF101763008",
    "submission_url": "https://codeforces.com/contest/1459/submission/101763008",
    "tags": [
      "dp",
      "math",
      "*1300"
    ],
    "timestamp": "Dec/19/2020 16:56"
  },
  "CF101770509": {
    "contest_id": 1459,
    "language": "GNU C++17 (64)",
    "path": "codeforces/1459/A.cpp",
    "problem_index": "A",
    "problem_name": "Red-Blue Shuffle",
    "problem_url": "https://codeforces.com/contest/1459/problem/A",
    "submission_id": "CF101770509",
    "submission_url": "https://codeforces.com/contest/1459/submission/101770509",
    "tags": [
      "math",
      "probabilities",
      "*800"
    ],
    "timestamp": "Dec/19/2020 18:06"
  },
  "CF101859643": {
    "contest_id": 1465,
    "language": "GNU C++17 (64)",
    "path": "codeforces/1465/A.cpp",
    "problem_index": "A",
    "problem_name": "In-game Chat",
    "problem_url": "https://codeforces.com/contest/1465/problem/A",
    "submission_id": "CF101859643",
    "submission_url": "https://codeforces.com/contest/1465/submission/101859643",
    "tags": [
      "implementation"
    ],
    "timestamp": "Dec/20/2020 20:36"
  },
  "CF101866974": {
    "contest_id": 1465,
    "language": "GNU C++17 (64)",
    "path": "codeforces/1465/B.cpp",
    "problem_index": "B",
    "problem_name": "Fair Numbers",
    "problem_url": "https://codeforces.com/contest/1465/problem/B",
    "submission_id": "CF101866974",
    "submission_url": "https://codeforces.com/contest/1465/submission/101866974",
    "tags": [
      "brute force",
      "number theory"
    ],
    "timestamp": "Dec/20/2020 20:42"
  }
}